CHANGELOG.txt
LICENSE.txt
MANIFEST.in
README.rst
requirements.txt
setup.cfg
setup.py
meieraha2/__init__.py
meieraha2/app.py
meieraha2/assets.py
meieraha2/config.py
meieraha2/i18n.py
meieraha2/manage.py
meieraha2/model.py
meieraha2/wsgi.py
meieraha2.egg-info/PKG-INFO
meieraha2.egg-info/SOURCES.txt
meieraha2.egg-info/dependency_links.txt
meieraha2.egg-info/entry_points.txt
meieraha2.egg-info/not-zip-safe
meieraha2.egg-info/pbr.json
meieraha2.egg-info/requires.txt
meieraha2.egg-info/top_level.txt
meieraha2/data/all_records_2014.txt
meieraha2/data/sample_dataset.json
meieraha2/data/sample_pasteconfig.ini
meieraha2/data/sample_settings.py
meieraha2/static/robots.txt
meieraha2/static/fonts/GraublauWeb.otf
meieraha2/static/fonts/GraublauWebPro.otf
meieraha2/static/fonts/GraublauWebPro.woff
meieraha2/static/fonts/estonia/meierahaicons.eot
meieraha2/static/fonts/estonia/meierahaicons.svg
meieraha2/static/fonts/estonia/meierahaicons.ttf
meieraha2/static/fonts/estonia/meierahaicons.woff
meieraha2/static/fonts/estonia/meierahaicons.woff2
meieraha2/static/fonts/gyumri/meierahaicons.eot
meieraha2/static/fonts/gyumri/meierahaicons.svg
meieraha2/static/fonts/gyumri/meierahaicons.ttf
meieraha2/static/fonts/gyumri/meierahaicons.woff
meieraha2/static/img/Thumbs.db
meieraha2/static/img/background-en.png
meieraha2/static/img/background-et.png
meieraha2/static/img/background-hy.png
meieraha2/static/img/comparisons/Thumbs.db
meieraha2/static/img/comparisons/kreekaeuro.jpg
meieraha2/static/img/comparisons/lennukid.jpg
meieraha2/static/img/comparisons/maantee.jpg
meieraha2/static/img/comparisons/opetaja.jpg
meieraha2/static/img/comparisons/sammas.jpg
meieraha2/static/img/comparisons/tootaja.jpg
meieraha2/static/img/comparisons/vangla.jpg
meieraha2/static/img/icons/estonia/android-chrome-144x144.png
meieraha2/static/img/icons/estonia/android-chrome-192x192.png
meieraha2/static/img/icons/estonia/android-chrome-36x36.png
meieraha2/static/img/icons/estonia/android-chrome-48x48.png
meieraha2/static/img/icons/estonia/android-chrome-72x72.png
meieraha2/static/img/icons/estonia/android-chrome-96x96.png
meieraha2/static/img/icons/estonia/apple-touch-icon-114x114.png
meieraha2/static/img/icons/estonia/apple-touch-icon-120x120.png
