Metadata-Version: 1.1
Name: meieraha2
Version: 2.2.2
Summary: Meieraha version 2
Home-page: http://meieraha.ee
Author: Konstantin Tretyakov, Tanel Kärp
Author-email: kt@ut.ee
License: MIT
Platform: UNKNOWN
Classifier: Development Status :: 5 - Production/Stable
Classifier: Framework :: Flask
Classifier: Programming Language :: Python
